mapna_mind_sdk-0.4.6.dist-info/DESCRIPTION.rst
mapna_mind_sdk-0.4.6.dist-info/METADATA
mapna_mind_sdk-0.4.6.dist-info/RECORD
mapna_mind_sdk-0.4.6.dist-info/WHEEL
mapna_mind_sdk-0.4.6.dist-info/metadata.json
mapna_mind_sdk-0.4.6.dist-info/sdk_test.py
mapna_mind_sdk-0.4.6.dist-info/top_level.txt
mapnamindsdk/Constants.py
mapnamindsdk/Mapper.py
mapnamindsdk/Mind.py
mapnamindsdk/Offline.py
mapnamindsdk/Online.py
mapnamindsdk/Rest.py
mapnamindsdk/WS.py
mapnamindsdk/__init__.py
mapnamindsdk/login_required.py
