Metadata-Version: 2.0
Name: mapna-mind-sdk
Version: 0.4.6
Summary: Mapna MIND Software Development Kit
Home-page: https://www.mapnaec.com
Author: Soheil Mehralian, Homa Hasannezhad, Afsaneh Sadeghnezhad
Author-email: mehralian1@gmail.com
License: UNKNOWN
Platform: UNKNOWN
Classifier: Programming Language :: Python :: 3
Classifier: License :: OSI Approved :: MIT License
Classifier: Operating System :: OS Independent
Requires-Python: >=3
